custom_fields-0.0.1.dist-info/METADATA
custom_fields-0.0.1.dist-info/RECORD
custom_fields-0.0.1.dist-info/WHEEL
custom_fields-0.0.1.dist-info/top_level.txt
fields/__init__.py
fields/cpf_cnpj.py
