Metadata-Version: 2.1
Name: custom-fields
Version: 0.0.1
Summary: Python module for brazilian validate CPF and CNPJ for Django.
Home-page: https://github.com/DanielBacci/custom_fields
Author: Daniel Bacci
Author-email: danielhdbacci@gmail.com
License: UNKNOWN
Download-URL: https://github.com/DanielBacci/custom_fields/tarball/master
Keywords: Django cpf cnpj validate form
Platform: UNKNOWN
Classifier: Intended Audience :: Developers
Classifier: License :: OSI Approved :: MIT License
Classifier: Operating System :: OS Independent
Classifier: Programming Language :: Python :: 2
Classifier: Programming Language :: Python :: 3
Requires-Dist: Django (>=1.8)
Requires-Dist: pycpfcnpj (==1.4)
